shipwright/__init__.py
shipwright/__main__.py
shipwright/exceptions.py
shipwright/targets.py
shipwright/_lib/__init__.py
shipwright/_lib/base.py
shipwright/_lib/build.py
shipwright/_lib/cache.py
shipwright/_lib/cli.py
shipwright/_lib/colors.py
shipwright/_lib/compat.py
shipwright/_lib/dependencies.py
shipwright/_lib/docker.py
shipwright/_lib/image.py
shipwright/_lib/msg.py
shipwright/_lib/push.py
shipwright/_lib/registry.py
shipwright/_lib/source_control.py
shipwright/_lib/tar.py
shipwright/_lib/targets.py
shipwright/_lib/zipper.py
shipwright-0.9.0.dist-info/DESCRIPTION.rst
shipwright-0.9.0.dist-info/METADATA
shipwright-0.9.0.dist-info/RECORD
shipwright-0.9.0.dist-info/WHEEL
shipwright-0.9.0.dist-info/entry_points.txt
shipwright-0.9.0.dist-info/metadata.json
shipwright-0.9.0.dist-info/top_level.txt
