Metadata-Version: 2.0
Name: shipwright
Version: 0.9.0
Summary: The right way to build, tag and ship shared Docker images.
Home-page: https://github.com/6si/shipwright/
Author: Scott Robertson
Author-email: scott@6sense.com
License: Apache Software License
Platform: any
Classifier: Programming Language :: Python
Classifier: Programming Language :: Python :: 2
Classifier: Programming Language :: Python :: 2.7
Classifier: Programming Language :: Python :: 3
Classifier: Programming Language :: Python :: 3.4
Classifier: Programming Language :: Python :: 3.5
Classifier: Programming Language :: Python :: 3.6
Classifier: Development Status :: 4 - Beta
Classifier: Natural Language :: English
Classifier: Intended Audience :: Developers
Classifier: License :: OSI Approved :: Apache Software License
Classifier: Operating System :: OS Independent
Classifier: Topic :: Software Development :: Libraries :: Python Modules
Requires-Dist: GitPython (<3.0.0,>=2.0.5)
Requires-Dist: docker (<3.0.0,>=2.0.1)
Provides-Extra: registry
Requires-Dist: docker-registry-client (>=0.5.1,<0.6.0); extra == 'registry'
